jopksf/__init__.py
jopkf-0.1.2.dist-info/LICENSE.txt
jopkf-0.1.2.dist-info/METADATA
jopkf-0.1.2.dist-info/WHEEL
jopkf-0.1.2.dist-info/top_level.txt
jopkf-0.1.2.dist-info/RECORD
